dreamberd/__init__.py
dreamberd/base.py
dreamberd/builtin.py
dreamberd/interpreter.py
dreamberd/processor/__init__.py
dreamberd/processor/expression_tree.py
dreamberd/processor/lexer.py
dreamberd/processor/syntax_tree.py
dreamberd/serialize.py
dreamberd-0.1.2.dist-info/LICENSE
dreamberd-0.1.2.dist-info/METADATA
dreamberd-0.1.2.dist-info/WHEEL
dreamberd-0.1.2.dist-info/entry_points.txt
dreamberd-0.1.2.dist-info/RECORD
