Metadata-Version: 2.1
Name: dreamberd
Version: 0.1.2
Summary: An interpreter for the perfect programming language, DreamBerd.
Author: Vivaan Singhvi
Author-email: singhvi.vivaan@gmail.com
Requires-Python: >=3.10,<4.0
Classifier: Programming Language :: Python :: 3
Classifier: Programming Language :: Python :: 3.10
Classifier: Programming Language :: Python :: 3.11
Classifier: Programming Language :: Python :: 3.12
Provides-Extra: globals
Provides-Extra: input
Requires-Dist: pygithub (==2.2.0) ; extra == "globals"
Requires-Dist: pynput (==1.7.6) ; extra == "input"
Requires-Dist: requests (==2.31.0)
